topsis_101917025/__init__.py
topsis_101917025/topsiscalc.py
Topsis_Gursangat_101917025-1.0.1.dist-info/LICENSE
Topsis_Gursangat_101917025-1.0.1.dist-info/METADATA
Topsis_Gursangat_101917025-1.0.1.dist-info/WHEEL
Topsis_Gursangat_101917025-1.0.1.dist-info/top_level.txt
Topsis_Gursangat_101917025-1.0.1.dist-info/RECORD
