Metadata-Version: 2.1
Name: Topsis-Gursangat-101917025
Version: 1.0.1
Summary: A package to find the topsis score
Author: Gursangat Singh
Author-email: gsingh11_be19@thapar.edu
License: UNKNOWN
Platform: UNKNOWN
Classifier: Programming Language :: Python :: 3
Classifier: License :: OSI Approved :: MIT License
Classifier: Operating System :: OS Independent
Requires-Python: >=3.6
License-File: LICENSE
Requires-Dist: requests
Requires-Dist: numpy
Requires-Dist: pandas
Requires-Dist: copy
